django_image_sitemaps-1.1.0.data/data/imagesitemaps/templates/image_sitemap.xml
imagesitemaps/__init__.py
imagesitemaps/models.py
imagesitemaps/tests.py
imagesitemaps/views.py
imagesitemaps/templates/__init__.py
imagesitemaps/templates/image_sitemap.xml
django_image_sitemaps-1.1.0.dist-info/LICENSE
django_image_sitemaps-1.1.0.dist-info/METADATA
django_image_sitemaps-1.1.0.dist-info/WHEEL
django_image_sitemaps-1.1.0.dist-info/top_level.txt
django_image_sitemaps-1.1.0.dist-info/RECORD
