Metadata-Version: 2.1
Name: django-image-sitemaps
Version: 1.1.0
Summary: Google Image Sitemaps builder for Django.
Home-page: https://github.com/akarzim/image-sitemaps/
Author: Francois Vantomme
Author-email: akarzim@gmail.com
License: BSD License
Keywords: google,django,image,sitemap
Platform: UNKNOWN
Classifier: Development Status :: 5 - Production/Stable
Classifier: Environment :: Web Environment
Classifier: Framework :: Django
Classifier: Intended Audience :: Developers
Classifier: Programming Language :: Python :: 2
Classifier: License :: OSI Approved :: BSD License
Classifier: Operating System :: OS Independent
Classifier: Topic :: Software Development
Classifier: Topic :: Internet
Classifier: Natural Language :: English
Requires-Dist: django (>=1.3)
